lcm_websocket_server/__init__.py
lcm_websocket_server/apps/__init__.py
lcm_websocket_server/apps/dial_proxy.py
lcm_websocket_server/apps/jpeg_proxy.py
lcm_websocket_server/apps/json_proxy.py
lcm_websocket_server/lib/__init__.py
lcm_websocket_server/lib/handler.py
lcm_websocket_server/lib/image.py
lcm_websocket_server/lib/lcm_utils/__init__.py
lcm_websocket_server/lib/lcm_utils/pubsub.py
lcm_websocket_server/lib/lcm_utils/types.py
lcm_websocket_server/lib/log.py
lcm_websocket_server/lib/server.py
lcm_websocket_server-0.2.1.dist-info/METADATA
lcm_websocket_server-0.2.1.dist-info/WHEEL
lcm_websocket_server-0.2.1.dist-info/entry_points.txt
lcm_websocket_server-0.2.1.dist-info/RECORD
