Metadata-Version: 2.1
Name: lcm-websocket-server
Version: 0.2.1
Summary: WebSocket server for republishing LCM messages
License: MIT
Author: Kevin Barnard
Author-email: kbarnard@mbari.org
Requires-Python: >=3.9,<4.0
Classifier: License :: OSI Approved :: MIT License
Classifier: Programming Language :: Python :: 3
Classifier: Programming Language :: Python :: 3.9
Classifier: Programming Language :: Python :: 3.10
Classifier: Programming Language :: Python :: 3.11
Classifier: Programming Language :: Python :: 3.12
Provides-Extra: image
Requires-Dist: compas-lcmtypes (==0.1.0) ; extra == "image"
Requires-Dist: lcmlog-py (>=0.1.0,<0.2.0)
Requires-Dist: numpy (>=1.26.4,<2.0.0) ; extra == "image"
Requires-Dist: opencv-python-headless (>=4.9.0.80,<5.0.0.0) ; extra == "image"
Requires-Dist: websockets (>=10.4,<11.0)
